{
    "key": "group_60dc060322d97",
    "title": "Event Settings",
    "fields": [
        {
            "key": "field_60dc06148afc6",
            "label": "Field Title",
            "name": "field_title",
            "type": "select",
            "instructions": "Select Option",
            "required": 0,
            "conditional_logic": 0,
            "wrapper": {
                "width": "",
                "class": "",
                "id": ""
            },
            "choices": {
                "Event Time": "Event Time",
                "Event Length": "Event Length",
                "Watch Time": "Watch Time"
            },
            "default_value": false,
            "allow_null": 0,
            "multiple": 0,
            "ui": 0,
            "return_format": "value",
            "ajax": 0,
            "placeholder": ""
        },
        {
            "key": "field_60dc065e8afc7",
            "label": "Duration Info",
            "name": "duration_info",
            "type": "text",
            "instructions": "",
            "required": 0,
            "conditional_logic": 0,
            "wrapper": {
                "width": "",
                "class": "",
                "id": ""
            },
            "default_value": "",
            "placeholder": "",
            "prepend": "",
            "append": "",
            "maxlength": ""
        },
        {
            "key": "field_60dc0da66a2c0",
            "label": "Event Date",
            "name": "event_date",
            "type": "date_picker",
            "instructions": "",
            "required": 0,
            "conditional_logic": 0,
            "wrapper": {
                "width": "",
                "class": "",
                "id": ""
            },
            "display_format": "d\/m\/Y",
            "return_format": "j F Y",
            "first_day": 1
        }
    ],
    "location": [
        [
            {
                "param": "post_parent",
                "operator": "==",
                "value": "12005"
            }
        ]
    ],
    "menu_order": 0,
    "position": "side",
    "style": "default",
    "label_placement": "top",
    "instruction_placement": "label",
    "hide_on_screen": "",
    "active": true,
    "description": "",
    "modified": 1626890121
}