{
    "key": "group_60ddf645bb976",
    "title": "Block: Single and Double Content with image and button Options",
    "fields": [
        {
            "key": "field_60ddf678dc9ca",
            "label": "Content Options",
            "name": "content_options",
            "type": "select",
            "instructions": "Select column options",
            "required": 0,
            "conditional_logic": 0,
            "wrapper": {
                "width": "",
                "class": "",
                "id": ""
            },
            "choices": {
                "single": "Single Column",
                "double": "2 Columns"
            },
            "default_value": false,
            "allow_null": 0,
            "multiple": 0,
            "ui": 0,
            "return_format": "value",
            "ajax": 0,
            "placeholder": ""
        },
        {
            "key": "field_60ddf7e6f3143",
            "label": "Single Content",
            "name": "single_content",
            "type": "flexible_content",
            "instructions": "",
            "required": 0,
            "conditional_logic": [
                [
                    {
                        "field": "field_60ddf678dc9ca",
                        "operator": "==contains",
                        "value": "single"
                    }
                ]
            ],
            "wrapper": {
                "width": "",
                "class": "",
                "id": ""
            },
            "layouts": {
                "layout_60ddf7f74e0fc": {
                    "key": "layout_60ddf7f74e0fc",
                    "name": "single_content",
                    "label": "Single Content",
                    "display": "block",
                    "sub_fields": [
                        {
                            "key": "field_60ddf7f9f3144",
                            "label": "Heading Title",
                            "name": "heading_title",
                            "type": "text",
                            "instructions": "",
                            "required": 0,
                            "conditional_logic": 0,
                            "wrapper": {
                                "width": "",
                                "class": "",
                                "id": ""
                            },
                            "default_value": "",
                            "placeholder": "",
                            "prepend": "",
                            "append": "",
                            "maxlength": ""
                        },
                        {
                            "key": "field_60ddf802f3145",
                            "label": "Single Content",
                            "name": "single_content",
                            "type": "wysiwyg",
                            "instructions": "",
                            "required": 0,
                            "conditional_logic": 0,
                            "wrapper": {
                                "width": "",
                                "class": "",
                                "id": ""
                            },
                            "default_value": "",
                            "tabs": "all",
                            "toolbar": "full",
                            "media_upload": 1,
                            "delay": 0
                        },
                        {
                            "key": "field_60ddf821f3146",
                            "label": "Add Image",
                            "name": "add_image",
                            "type": "true_false",
                            "instructions": "",
                            "required": 0,
                            "conditional_logic": 0,
                            "wrapper": {
                                "width": "",
                                "class": "",
                                "id": ""
                            },
                            "message": "(Optional)",
                            "default_value": 0,
                            "ui": 1,
                            "ui_on_text": "",
                            "ui_off_text": ""
                        },
                        {
                            "key": "field_60ddf864f3147",
                            "label": "Image",
                            "name": "image",
                            "type": "image",
                            "instructions": "",
                            "required": 0,
                            "conditional_logic": [
                                [
                                    {
                                        "field": "field_60ddf821f3146",
                                        "operator": "==",
                                        "value": "1"
                                    }
                                ]
                            ],
                            "wrapper": {
                                "width": "",
                                "class": "",
                                "id": ""
                            },
                            "return_format": "id",
                            "preview_size": "large",
                            "library": "all",
                            "min_width": "",
                            "min_height": "",
                            "min_size": "",
                            "max_width": "",
                            "max_height": "",
                            "max_size": "",
                            "mime_types": ""
                        },
                        {
                            "key": "field_60ddf9d2c9cad",
                            "label": "Button Link",
                            "name": "button_link",
                            "type": "link",
                            "instructions": "",
                            "required": 0,
                            "conditional_logic": 0,
                            "wrapper": {
                                "width": "",
                                "class": "",
                                "id": ""
                            },
                            "return_format": "array"
                        }
                    ],
                    "min": "",
                    "max": ""
                }
            },
            "button_label": "Add Row",
            "min": "",
            "max": ""
        },
        {
            "key": "field_60ddfb3808295",
            "label": "Double Column Content",
            "name": "double_content",
            "type": "flexible_content",
            "instructions": "",
            "required": 0,
            "conditional_logic": [
                [
                    {
                        "field": "field_60ddf678dc9ca",
                        "operator": "==contains",
                        "value": "double"
                    }
                ]
            ],
            "wrapper": {
                "width": "",
                "class": "",
                "id": ""
            },
            "layouts": {
                "layout_60ddf7f74e0fc": {
                    "key": "layout_60ddf7f74e0fc",
                    "name": "2_column_content",
                    "label": "2 Column Content",
                    "display": "block",
                    "sub_fields": [
                        {
                            "key": "field_60ddfb680829b",
                            "label": "Add Column",
                            "name": "add_column",
                            "type": "repeater",
                            "instructions": "",
                            "required": 0,
                            "conditional_logic": 0,
                            "wrapper": {
                                "width": "",
                                "class": "",
                                "id": ""
                            },
                            "collapsed": "",
                            "min": 0,
                            "max": 0,
                            "layout": "row",
                            "button_label": "",
                            "sub_fields": [
                                {
                                    "key": "field_60ddfb8c0829c",
                                    "label": "Heading",
                                    "name": "heading",
                                    "type": "text",
                                    "instructions": "",
                                    "required": 0,
                                    "conditional_logic": 0,
                                    "wrapper": {
                                        "width": "",
                                        "class": "",
                                        "id": ""
                                    },
                                    "default_value": "",
                                    "placeholder": "",
                                    "prepend": "",
                                    "append": "",
                                    "maxlength": ""
                                },
                                {
                                    "key": "field_60ddfb910829d",
                                    "label": "Content",
                                    "name": "content",
                                    "type": "wysiwyg",
                                    "instructions": "",
                                    "required": 0,
                                    "conditional_logic": 0,
                                    "wrapper": {
                                        "width": "",
                                        "class": "",
                                        "id": ""
                                    },
                                    "default_value": "",
                                    "tabs": "all",
                                    "toolbar": "full",
                                    "media_upload": 1,
                                    "delay": 0
                                },
                                {
                                    "key": "field_60ddfb960829e",
                                    "label": "Add Image",
                                    "name": "add_image",
                                    "type": "true_false",
                                    "instructions": "",
                                    "required": 0,
                                    "conditional_logic": 0,
                                    "wrapper": {
                                        "width": "",
                                        "class": "",
                                        "id": ""
                                    },
                                    "message": "(optional)",
                                    "default_value": 0,
                                    "ui": 1,
                                    "ui_on_text": "",
                                    "ui_off_text": ""
                                },
                                {
                                    "key": "field_60ddfbb40829f",
                                    "label": "Image",
                                    "name": "image",
                                    "type": "image",
                                    "instructions": "",
                                    "required": 0,
                                    "conditional_logic": [
                                        [
                                            {
                                                "field": "field_60ddfb960829e",
                                                "operator": "==",
                                                "value": "1"
                                            }
                                        ]
                                    ],
                                    "wrapper": {
                                        "width": "",
                                        "class": "",
                                        "id": ""
                                    },
                                    "return_format": "id",
                                    "preview_size": "large",
                                    "library": "all",
                                    "min_width": "",
                                    "min_height": "",
                                    "min_size": "",
                                    "max_width": "",
                                    "max_height": "",
                                    "max_size": "",
                                    "mime_types": ""
                                },
                                {
                                    "key": "field_60ddfbd7082a0",
                                    "label": "Button Link",
                                    "name": "button_link",
                                    "type": "link",
                                    "instructions": "",
                                    "required": 0,
                                    "conditional_logic": 0,
                                    "wrapper": {
                                        "width": "",
                                        "class": "",
                                        "id": ""
                                    },
                                    "return_format": "array"
                                },
                                {
                                    "key": "field_60e634f791ccd",
                                    "label": "Column Width",
                                    "name": "column_width",
                                    "type": "select",
                                    "instructions": "",
                                    "required": 0,
                                    "conditional_logic": 0,
                                    "wrapper": {
                                        "width": "",
                                        "class": "",
                                        "id": ""
                                    },
                                    "choices": {
                                        "3": "1\/4 Width",
                                        "4": "1\/3 Width",
                                        "5": "5\/12 Width",
                                        "6": "1\/2 Width",
                                        "7": "7\/12 Width",
                                        "8": "2\/3 Width",
                                        "9": "3\/4 Width"
                                    },
                                    "default_value": 5,
                                    "allow_null": 0,
                                    "multiple": 0,
                                    "ui": 0,
                                    "return_format": "value",
                                    "ajax": 0,
                                    "placeholder": ""
                                }
                            ]
                        }
                    ],
                    "min": "",
                    "max": ""
                }
            },
            "button_label": "Add Row",
            "min": "",
            "max": ""
        }
    ],
    "location": [
        [
            {
                "param": "block",
                "operator": "==",
                "value": "acf\/column-content-options"
            }
        ]
    ],
    "menu_order": 0,
    "position": "normal",
    "style": "default",
    "label_placement": "top",
    "instruction_placement": "label",
    "hide_on_screen": "",
    "active": true,
    "description": "",
    "modified": 1625699985
}